{
  "carriage": [
    {
      "A_left": {
        "楼兰-楼兰": 2.0
      },
      "A_right": {},
      "B_left": {},
      "B_right": {
        "长安系列（含河北.南京）-1026SIN(双排)": 1.0,
        "重庆渝安车型尺寸表-V27": 1.0
      },
      "C": {
        "重庆渝安车型尺寸表-K05(厢车)": 1.0
      },
      "D_left": {
        "五菱-1029": 2.0
      },
      "D_right": {
        "长安系列（含河北.南京）-逸动": 1.0
      },
      "E": {
        "长安系列（含河北.南京）-1026SIN(双排)": 2.0
      },
      "pi_left": 0,
      "pi_right": 0
    },
    {
      "A_left": {
        "重庆现代-拉菲斯塔": 1.0
      },
      "A_right": {
        "楼兰-楼兰": 1.0
      },
      "B_left": {
        "五菱-6465": 1.0
      },
      "B_right": {
        "重庆渝安车型尺寸表-V27": 1.0
      },
      "C": {
        "重庆渝安车型尺寸表-K05(厢车)": 1.0
      },
      "D_left": {
        "长安系列（含河北.南京）-CS75": 1.0,
        "五菱-6465": 1.0,
        "重庆现代-拉菲斯塔": 2.0
      },
      "D_right": {},
      "E": {
        "重庆渝安车型尺寸表-V27": 1.0
      },
      "pi_left": 0,
      "pi_right": 1
    },
    {
      "A_left": {
        "长安系列（含河北.南京）-逸动": 1.0
      },
      "A_right": {
        "楼兰-楼兰": 1.0
      },
      "B_left": {
        "五菱-6465": 1.0,
        "五菱-1029": 1.0
      },
      "B_right": {
        "重庆渝安车型尺寸表-V27": 1.0
      },
      "C": {},
      "D_left": {
        "长安系列（含河北.南京）-CS75": 1.0,
        "重庆渝安车型尺寸表-V27": 1.0,
        "长安系列（含河北.南京）-逸动": 1.0
      },
      "D_right": {
        "重庆现代-拉菲斯塔": 2.0
      },
      "E": {},
      "pi_left": 0,
      "pi_right": 0
    },
    {
      "A_left": {},
      "A_right": {
        "楼兰-楼兰": 1.0,
        "长安系列（含河北.南京）-逸动": 1.0
      },
      "B_left": {
        "五菱-6465": 1.0,
        "五菱-1029": 1.0
      },
      "B_right": {
        "重庆渝安车型尺寸表-V27": 1.0
      },
      "C": {},
      "D_left": {
        "重庆现代-拉菲斯塔": 2.0
      },
      "D_right": {
        "长安系列（含河北.南京）-1026SIN(双排)": 3.0
      },
      "E": {},
      "pi_left": 0,
      "pi_right": 0
    },
    {
      "A_left": {},
      "A_right": {
        "长安系列（含河北.南京）-逸动": 2.0
      },
      "B_left": {
        "重庆渝安车型尺寸表-V27": 1.0,
        "长安系列（含河北.南京）-1029SC4": 1.0
      },
      "B_right": {
        "长安系列（含河北.南京）-1026SIN(双排)": 1.0
      },
      "C": {},
      "D_left": {
        "重庆渝安车型尺寸表-V27": 2.0,
        "长安系列（含河北.南京）-1029SC4": 1.0,
        "五菱-1029": 1.0
      },
      "D_right": {
        "长安系列（含河北.南京）-1029SC4": 1.0
      },
      "E": {},
      "pi_left": 0,
      "pi_right": 0
    },
    {
      "A_left": {},
      "A_right": {
        "楼兰-楼兰": 2.0
      },
      "B_left": {
        "长安系列（含河北.南京）-1026SIN(双排)": 1.0,
        "重庆渝安车型尺寸表-V27": 1.0
      },
      "B_right": {},
      "C": {
        "重庆渝安车型尺寸表-K05(厢车)": 1.0
      },
      "D_left": {
        "长安系列（含河北.南京）-1026SIN(双排)": 2.0
      },
      "D_right": {
        "五菱-6465": 1.0,
        "五菱-1029": 2.0
      },
      "E": {},
      "pi_left": 0,
      "pi_right": 0
    },
    {
      "A_left": {},
      "A_right": {
        "长安系列（含河北.南京）-CS75": 1.0,
        "五菱-6465": 1.0
      },
      "B_left": {
        "长安系列（含河北.南京）-1026SIN(双排)": 2.0
      },
      "B_right": {
        "五菱-1029": 1.0
      },
      "C": {},
      "D_left": {
        "重庆现代-拉菲斯塔": 1.0
      },
      "D_right": {
        "长安系列（含河北.南京）-CS75": 1.0,
        "重庆现代-拉菲斯塔": 1.0,
        "长安系列（含河北.南京）-逸动": 1.0
      },
      "E": {
        "重庆渝安车型尺寸表-V27": 1.0
      },
      "pi_left": 1,
      "pi_right": 1
    },
    {
      "A_left": {
        "楼兰-楼兰": 1.0,
        "长安系列（含河北.南京）-逸动": 2.0
      },
      "A_right": {},
      "B_left": {},
      "B_right": {
        "重庆渝安车型尺寸表-V27": 1.0,
        "五菱-1029": 1.0
      },
      "C": {},
      "D_left": {
        "长安系列（含河北.南京）-1026SIN(双排)": 2.0,
        "五菱-1029": 2.0
      },
      "D_right": {
        "长安系列（含河北.南京）-逸动": 1.0
      },
      "E": {},
      "pi_left": 0,
      "pi_right": 0
    },
    {
      "A_left": {},
      "A_right": {
        "长安系列（含河北.南京）-逸动": 2.0
      },
      "B_left": {
        "长安系列（含河北.南京）-1026SIN(双排)": 1.0,
        "重庆渝安车型尺寸表-V27": 1.0,
        "长安系列（含河北.南京）-1029SC4": 1.0
      },
      "B_right": {},
      "C": {},
      "D_left": {},
      "D_right": {
        "长安系列（含河北.南京）-CS75": 1.0,
        "重庆渝安车型尺寸表-V27": 1.0,
        "五菱-6465": 1.0,
        "重庆现代-拉菲斯塔": 2.0
      },
      "E": {},
      "pi_left": 1,
      "pi_right": 0
    },
    {
      "A_left": {
        "长安系列（含河北.南京）-CS75": 1.0
      },
      "A_right": {
        "重庆现代-拉菲斯塔": 1.0
      },
      "B_left": {
        "长安系列（含河北.南京）-1026SIN(双排)": 1.0
      },
      "B_right": {
        "长安系列（含河北.南京）-1026SIN(双排)": 1.0
      },
      "C": {
        "重庆渝安车型尺寸表-K05(厢车)": 1.0
      },
      "D_left": {},
      "D_right": {
        "长安系列（含河北.南京）-1026SIN(双排)": 2.0,
        "五菱-6465": 1.0,
        "五菱-1029": 2.0
      },
      "E": {},
      "pi_left": 1,
      "pi_right": 0
    }
  ]
}